prostlab/__init__.py
prostlab/cached_revision.py
prostlab/experiment.py
prostlab/repeated_pattern_parser.py
prostlab/suites.py
prostlab/parsers/__init__.py
prostlab/parsers/ids-parser.py
prostlab/parsers/prost-parser.py
prostlab/parsers/thts-parser.py
prostlab/reports/__init__.py
prostlab/reports/absolute.py
prostlab-1.1.dist-info/LICENSE
prostlab-1.1.dist-info/METADATA
prostlab-1.1.dist-info/WHEEL
prostlab-1.1.dist-info/top_level.txt
prostlab-1.1.dist-info/RECORD
