Metadata-Version: 2.1
Name: prostlab
Version: 1.1
Summary: Perform experiments with the Prost planner
Home-page: https://github.com/prost-planner/prostlab
Author: Thomas Keller
Author-email: thomaskeller79@gmail.com
License: GPL3+
Keywords: experiment lab Prost
Platform: UNKNOWN
Classifier: Development Status :: 5 - Production/Stable
Classifier: Environment :: Console
Classifier: Intended Audience :: Science/Research
Classifier: License :: OSI Approved :: GNU General Public License v3 or later (GPLv3+)
Classifier: Programming Language :: Python :: 3
Classifier: Topic :: Scientific/Engineering
Requires-Python: >=3.6
Requires-Dist: lab (==6.3)
